{"cameraMode":{"drawMode":0,"name":"Shaded","section":"Shading Mode"},"sceneLighting":true,"audioPlay":false,"sceneViewState":{"m_AlwaysRefresh":false,"showFog":true,"showSkybox":true,"showFlares":true,"showImageEffects":true,"showParticleSystems":true,"showVisualEffectGraphs":true,"m_FxEnabled":true},"in2DMode":false,"pivot":{"x":49.95683288574219,"y":0.9126197099685669,"z":0.003662597853690386},"rotation":{"x":0.17510738968849183,"y":-0.10316986590623856,"z":0.01845378614962101,"w":0.9789544343948364},"size":392.09722900390627,"orthographic":false}